README.md
setup.py
stylelens_s3/__init__.py
stylelens_s3/s3.py
stylelens_s3.egg-info/PKG-INFO
stylelens_s3.egg-info/SOURCES.txt
stylelens_s3.egg-info/dependency_links.txt
stylelens_s3.egg-info/requires.txt
stylelens_s3.egg-info/top_level.txt