Metadata-Version: 1.0
Name: stylelens-s3
Version: 0.0.2
Summary: stylelens-s3
Home-page: UNKNOWN
Author: UNKNOWN
Author-email: master@bluehack.net
License: UNKNOWN
Keywords: BlueLens,stylelens-s3
Platform: UNKNOWN
